Metadata-Version: 1.1
Name: salsita-gitflow
Version: 1.1.1
Summary: Git extensions to provide high-level repository operations for Vincent Driessen's branching model.
Home-page: http://github.com/salsita/gitflow/
Author: Ondrej Kupka, Tomas Brambora, Hartmut Goebelm, Vincent Driessen
Author-email: ondrejk@salsitasoft.com, tomas@salsitasoft.com, h.goebel@crazy-compilers.com, vincent@datafox.nl
License: BSD
Platform: any
Classifier: Development Status :: 4 - Beta
Classifier: Environment :: Console
Classifier: Intended Audience :: Developers
Classifier: License :: OSI Approved :: BSD License
Classifier: Operating System :: OS Independent
Classifier: Operating System :: POSIX
Classifier: Programming Language :: Python
Classifier: Topic :: Software Development :: Version Control
